myMean/__init__.py
myMean-0.0.3.dist-info/METADATA
myMean-0.0.3.dist-info/WHEEL
myMean-0.0.3.dist-info/top_level.txt
myMean-0.0.3.dist-info/RECORD
