Metadata-Version: 2.1
Name: myMean
Version: 0.0.3
Summary: UNKNOWN
Home-page: UNKNOWN
Author: Ani Chattaraj
Author-email: UNKNOWN
License: UNKNOWN
Platform: UNKNOWN
Classifier: Programming Language :: Python :: 3
Classifier: License :: OSI Approved :: MIT License
Classifier: Operating System :: OS Independent
Requires-Dist: numpy
